setup.py
pyjmdict/__init__.py
pyjmdict/main.py
pyjmdict.egg-info/PKG-INFO
pyjmdict.egg-info/SOURCES.txt
pyjmdict.egg-info/dependency_links.txt
pyjmdict.egg-info/requires.txt
pyjmdict.egg-info/top_level.txt
pyjmdict.egg-info/zip-safe
pyjmdict/db/__init__.py
pyjmdict/db/jmdict.py
pyjmdict/db/kanjidic.py
pyjmdict/db/kanjidic_txt.py
pyjmdict/tests/__init__.py
pyjmdict/tests/test.py