Metadata-Version: 1.1
Name: pyjmdict
Version: 0.4.5
Summary: JMDict sqlalchemy interface
Home-page: https://hydra.bacontoast.org/f/pyjmdict/
Author: jikan@cock.li
Author-email: jikan@cock.li
License: LGPLv3
Platform: UNKNOWN
Classifier: Programming Language :: Python :: 3 :: Only
